my_bank/__init__.py
my_bank/deposit.py
my_bank/removal.py
my_bank-0.0.1.dist-info/METADATA
my_bank-0.0.1.dist-info/WHEEL
my_bank-0.0.1.dist-info/top_level.txt
my_bank-0.0.1.dist-info/RECORD
