Metadata-Version: 2.1
Name: my_bank
Version: 0.0.1
Summary: Realize bank operations
Author: Patrick Magalhães
Author-email: prm.rp2@icloud.com
Requires-Python: >=3.8
